pony-stubs/__init__.pyi
pony-stubs/converting.pyi
pony-stubs/flask/__init__.pyi
pony-stubs/options.pyi
pony-stubs/orm/__init__.pyi
pony-stubs/orm/asttranslation.pyi
pony-stubs/orm/core.pyi
pony-stubs/orm/dbapiprovider.pyi
pony-stubs/orm/dbproviders/__init__.pyi
pony-stubs/orm/dbproviders/cockroach.pyi
pony-stubs/orm/dbproviders/mysql.pyi
pony-stubs/orm/dbproviders/oracle.pyi
pony-stubs/orm/dbproviders/postgres.pyi
pony-stubs/orm/dbproviders/sqlite.pyi
pony-stubs/orm/dbschema.pyi
pony-stubs/orm/decompiling.pyi
pony-stubs/orm/integration/__init__.pyi
pony-stubs/orm/integration/bottle_plugin.pyi
pony-stubs/orm/ormtypes.pyi
pony-stubs/orm/serialization.pyi
pony-stubs/orm/sqlbuilding.pyi
pony-stubs/orm/sqlsymbols.pyi
pony-stubs/orm/sqltranslation.pyi
pony-stubs/py23compat.pyi
pony-stubs/thirdparty/__init__.pyi
pony-stubs/thirdparty/decorator.pyi
pony-stubs/utils/__init__.pyi
pony-stubs/utils/properties.pyi
pony-stubs/utils/utils.pyi
pony_stubs-0.5.2.dist-info/LICENSE.md
pony_stubs-0.5.2.dist-info/WHEEL
pony_stubs-0.5.2.dist-info/METADATA
pony_stubs-0.5.2.dist-info/RECORD
