Metadata-Version: 2.1
Name: pony-stubs
Version: 0.5.2
Summary: Type stubs for Pony ORM
Home-page: https://github.com/Jonesus/pony-stubs
License: MIT
Keywords: pony,types,stubs,mypy,pyright
Author: Joonas Palosuo
Author-email: joonas.palosuo@gmail.com
Requires-Python: >=3.7,<4.0
Classifier: License :: OSI Approved :: MIT License
Classifier: Programming Language :: Python :: 3
Classifier: Programming Language :: Python :: 3.10
Classifier: Programming Language :: Python :: 3.7
Classifier: Programming Language :: Python :: 3.8
Classifier: Programming Language :: Python :: 3.9
Project-URL: Repository, https://github.com/Jonesus/pony-stubs
